Metadata-Version: 2.1
Name: green_gold
Version: 0.1.1
Summary: green-gold
Home-page: https://radioframenetworks.com/jacknote
Author: jdev
Author-email: jdev@radioframenetworks.com
